<log><log_entry><action>Executed: echo Hello, World!</action><timestamp>2024-10-17T15:50:44.383210</timestamp></log_entry><log_entry><action>Executed: ls /</action><timestamp>2024-10-17T15:50:44.383786</timestamp></log_entry><log_entry><action>Executed: uptime</action><timestamp>2024-10-17T15:50:44.383986</timestamp></log_entry><log_entry><action>Executed: uptime</action><timestamp>2024-10-17T15:50:49.604478</timestamp></log_entry><log_entry><action>Executed: echo hello</action><timestamp>2024-10-17T15:50:55.389981</timestamp></log_entry><log_entry><action>Executed: ls</action><timestamp>2024-10-17T15:51:27.150562</timestamp></log_entry><log_entry><action>Executed: cd asd</action><timestamp>2024-10-17T15:51:32.589125</timestamp></log_entry><log_entry><action>Exit command executed.</action><timestamp>2024-10-17T15:51:40.461300</timestamp></log_entry></log>